README.md
setup.cfg
setup.py
zinc/__init__.py
zinc/middleware.py
zinc/models.py
zinc/ns_check.py
zinc/pagination.py
zinc/tasks.py
zinc/urls.py
zinc/validators.py
zinc/views.py
zinc/admin/__init__.py
zinc/admin/ip.py
zinc/admin/policy.py
zinc/admin/policy_record.py
zinc/admin/soft_delete.py
zinc/admin/zone.py
zinc/management/__init__.py
zinc/management/commands/__init__.py
zinc/management/commands/cleanup_stale_zones.py
zinc/management/commands/reconcile_healthchecks.py
zinc/management/commands/reconcile_policy_records.py
zinc/management/commands/reconcile_zones.py
zinc/management/commands/seed.py
zinc/management/commands/update_ns_propagated.py
zinc/migrations/0001_initial.py
zinc/migrations/0002_auto_20170309_1144.py
zinc/migrations/0003_zone_ns_propagated.py
zinc/migrations/0004_zone_cached_ns_records.py
zinc/migrations/0005_policymember_enabled.py
zinc/migrations/0006_auto_20170414_0936.py
zinc/migrations/0007_policy_routing.py
zinc/migrations/0008_set_routing_policy.py
zinc/migrations/__init__.py
zinc/route53/__init__.py
zinc/route53/client.py
zinc/route53/health_check.py
zinc/route53/policy.py
zinc/route53/record.py
zinc/route53/zone.py
zinc/serializers/__init__.py
zinc/serializers/policy.py
zinc/serializers/record.py
zinc/serializers/zone.py
zinc/utils/__init__.py
zinc/utils/generators.py
zinc/utils/validation.py
zinc_dns.egg-info/PKG-INFO
zinc_dns.egg-info/SOURCES.txt
zinc_dns.egg-info/dependency_links.txt
zinc_dns.egg-info/requires.txt
zinc_dns.egg-info/top_level.txt